{
  "global_settings": {},
  "levels": [
    {
      "id": "L_AUTO_1775321891358_0",
      "kategori": "kuis",
      "pertanyaan": "Tubuh Kita: Kita melihat menggunakan?",
      "item_target": {
        "nama": "Mata",
        "isTarget": true
      },
      "item_pengecoh": [
        {
          "nama": "Telinga",
          "isTarget": false
        },
        {
          "nama": "Kaki",
          "isTarget": false
        },
        {
          "nama": "Tangan",
          "isTarget": false
        }
      ]
    },
    {
      "id": "L_AUTO_1775321891358_1",
      "kategori": "urutan",
      "pertanyaan": "Logika: Urutkan angka 1 sampai 4!",
      "item_urutan": [
        {
          "nama": "Satu 1",
          "indexAsli": 0
        },
        {
          "nama": "Dua 2",
          "indexAsli": 1
        },
        {
          "nama": "Tiga 3",
          "indexAsli": 2
        },
        {
          "nama": "Empat 4",
          "indexAsli": 3
        }
      ]
    },
    {
      "id": "L_AUTO_1775321891358_2",
      "kategori": "kuis",
      "pertanyaan": "Hewan Darat: Mana yang termasuk hewan peliharaan?",
      "item_target": {
        "nama": "Kucing",
        "isTarget": true
      },
      "item_pengecoh": [
        {
          "nama": "Harimau",
          "isTarget": false
        },
        {
          "nama": "Buaya",
          "isTarget": false
        },
        {
          "nama": "Hiu",
          "isTarget": false
        }
      ]
    },
    {
      "id": "L_AUTO_1775321891358_3",
      "kategori": "drag",
      "pertanyaan": "Kendaraan: Tarik perahu ke kotak air!",
      "item_target": {
        "nama": "Perahu",
        "isTarget": true
      },
      "item_pengecoh": [
        {
          "nama": "Mobil",
          "isTarget": false
        },
        {
          "nama": "Sepeda",
          "isTarget": false
        }
      ]
    },
    {
      "id": "L_AUTO_1775321891358_4",
      "kategori": "kuis",
      "pertanyaan": "Matematika: Ada berapa jumlah matahari ini? ☀️☀️",
      "item_target": {
        "nama": "Dua",
        "isTarget": true
      },
      "item_pengecoh": [
        {
          "nama": "Satu",
          "isTarget": false
        },
        {
          "nama": "Tiga",
          "isTarget": false
        },
        {
          "nama": "Empat",
          "isTarget": false
        }
      ]
    },
    {
      "id": "L_AUTO_1775321896273_0",
      "kategori": "kuis",
      "pertanyaan": "Warna: Warna apa daun pada pohon?",
      "item_target": {
        "nama": "Hijau",
        "isTarget": true
      },
      "item_pengecoh": [
        {
          "nama": "Merah",
          "isTarget": false
        },
        {
          "nama": "Biru",
          "isTarget": false
        },
        {
          "nama": "Kuning",
          "isTarget": false
        }
      ]
    },
    {
      "id": "L_AUTO_1775321896273_1",
      "kategori": "drag",
      "pertanyaan": "Sains: Tarik awan ke langit (kotak)!",
      "item_target": {
        "nama": "Awan",
        "isTarget": true
      },
      "item_pengecoh": [
        {
          "nama": "Batu",
          "isTarget": false
        },
        {
          "nama": "Kayu",
          "isTarget": false
        }
      ]
    },
    {
      "id": "L_AUTO_1775321896273_2",
      "kategori": "kuis",
      "pertanyaan": "Akhlaq: Jika diberi hadiah, kita harus bilang apa?",
      "item_target": {
        "nama": "Terima Kasih",
        "isTarget": true
      },
      "item_pengecoh": [
        {
          "nama": "Marah",
          "isTarget": false
        },
        {
          "nama": "Diam",
          "isTarget": false
        },
        {
          "nama": "Nangis",
          "isTarget": false
        }
      ]
    },
    {
      "id": "L_AUTO_1775321896273_3",
      "kategori": "memory",
      "pertanyaan": "Ingatan: Cocokkan buah yang sama!",
      "item_target": {
        "nama": "Apel",
        "isTarget": true
      },
      "item_pengecoh": [
        {
          "nama": "Pisang",
          "isTarget": false
        },
        {
          "nama": "Jeruk",
          "isTarget": false
        },
        {
          "nama": "Anggur",
          "isTarget": false
        }
      ]
    },
    {
      "id": "L_AUTO_1775321896273_4",
      "kategori": "urutan",
      "pertanyaan": "Sains: Urutkan dari pagi ke malam!",
      "item_urutan": [
        {
          "nama": "Matahari Terbit",
          "indexAsli": 0
        },
        {
          "nama": "Siang Terang",
          "indexAsli": 1
        },
        {
          "nama": "Sore",
          "indexAsli": 2
        },
        {
          "nama": "Bulan Bintang",
          "indexAsli": 3
        }
      ]
    },
    {
      "kategori": "drag",
      "pertanyaan": "Mengenal Hewan: Tarik \"Kuda 🐎\" ke dalam kotak!",
      "item_target": {
        "nama": "Kuda 🐎",
        "isTarget": true
      },
      "item_pengecoh": [
        {
          "nama": "Bebek 🐔",
          "isTarget": false
        },
        {
          "nama": "Ikan 🐟",
          "isTarget": false
        },
        {
          "nama": "Gajah 🐘",
          "isTarget": false
        }
      ],
      "id": "L_AUTO_1775323250539_0"
    },
    {
      "kategori": "drag",
      "pertanyaan": "Mengenal Hewan: Tarik \"Burung 🐦\" ke dalam kotak!",
      "item_target": {
        "nama": "Burung 🐦",
        "isTarget": true
      },
      "item_pengecoh": [
        {
          "nama": "Anjing 🐶",
          "isTarget": false
        },
        {
          "nama": "Ikan 🐟",
          "isTarget": false
        },
        {
          "nama": "Kuda 🐎",
          "isTarget": false
        }
      ],
      "id": "L_AUTO_1775323250539_1"
    },
    {
      "kategori": "drag",
      "pertanyaan": "Mengenal Buah: Tarik \"Anggur 🍇\" ke dalam kotak!",
      "item_target": {
        "nama": "Anggur 🍇",
        "isTarget": true
      },
      "item_pengecoh": [
        {
          "nama": "Pisang 🍌",
          "isTarget": false
        },
        {
          "nama": "Apel 🍎",
          "isTarget": false
        },
        {
          "nama": "Ceri 🍒",
          "isTarget": false
        }
      ],
      "id": "L_AUTO_1775323250539_2"
    },
    {
      "kategori": "memory",
      "pertanyaan": "Latih Ingatan: Cari pasangan gambar yang sama!",
      "item_target": {
        "nama": "Apel 🍎",
        "isTarget": true
      },
      "item_pengecoh": [
        {
          "nama": "Semangka 🍉",
          "isTarget": false
        },
        {
          "nama": "Ceri 🍒",
          "isTarget": false
        }
      ],
      "id": "L_AUTO_1775323250539_3"
    },
    {
      "kategori": "memory",
      "pertanyaan": "Latih Ingatan: Cari pasangan gambar yang sama!",
      "item_target": {
        "nama": "Stroberi 🍓",
        "isTarget": true
      },
      "item_pengecoh": [
        {
          "nama": "Apel 🍎",
          "isTarget": false
        },
        {
          "nama": "Pisang 🍌",
          "isTarget": false
        }
      ],
      "id": "L_AUTO_1775323250539_4"
    },
    {
      "kategori": "urutan",
      "pertanyaan": "Urutkan angka dari yang terkecil ke terbesar!",
      "item_urutan": [
        {
          "nama": "Angka 1",
          "indexAsli": 0
        },
        {
          "nama": "Angka 2",
          "indexAsli": 1
        },
        {
          "nama": "Angka 3",
          "indexAsli": 2
        },
        {
          "nama": "Angka 4",
          "indexAsli": 3
        }
      ],
      "id": "L_AUTO_1775323258148_0"
    },
    {
      "kategori": "drag",
      "pertanyaan": "Mengenal Buah: Tarik \"Ceri 🍒\" ke dalam kotak!",
      "item_target": {
        "nama": "Ceri 🍒",
        "isTarget": true
      },
      "item_pengecoh": [
        {
          "nama": "Pisang 🍌",
          "isTarget": false
        },
        {
          "nama": "Nanas 🍍",
          "isTarget": false
        },
        {
          "nama": "Apel 🍎",
          "isTarget": false
        }
      ],
      "id": "L_AUTO_1775323258148_1"
    },
    {
      "kategori": "drag",
      "pertanyaan": "Mengenal Buah: Tarik \"Semangka 🍉\" ke dalam kotak!",
      "item_target": {
        "nama": "Semangka 🍉",
        "isTarget": true
      },
      "item_pengecoh": [
        {
          "nama": "Anggur 🍇",
          "isTarget": false
        },
        {
          "nama": "Jeruk 🍊",
          "isTarget": false
        },
        {
          "nama": "Pisang 🍌",
          "isTarget": false
        }
      ],
      "id": "L_AUTO_1775323263068_0"
    },
    {
      "kategori": "memory",
      "pertanyaan": "Latih Ingatan: Cari pasangan gambar yang sama!",
      "item_target": {
        "nama": "Ceri 🍒",
        "isTarget": true
      },
      "item_pengecoh": [
        {
          "nama": "Nanas 🍍",
          "isTarget": false
        },
        {
          "nama": "Mangga 🥭",
          "isTarget": false
        }
      ],
      "id": "L_AUTO_1775323263068_1"
    },
    {
      "kategori": "memory",
      "pertanyaan": "Latih Ingatan: Cari pasangan gambar yang sama!",
      "item_target": {
        "nama": "Nanas 🍍",
        "isTarget": true
      },
      "item_pengecoh": [
        {
          "nama": "Pisang 🍌",
          "isTarget": false
        },
        {
          "nama": "Stroberi 🍓",
          "isTarget": false
        }
      ],
      "id": "L_AUTO_1775323263068_2"
    },
    {
      "kategori": "memory",
      "pertanyaan": "Latih Ingatan: Cari pasangan gambar yang sama!",
      "item_target": {
        "nama": "Mangga 🥭",
        "isTarget": true
      },
      "item_pengecoh": [
        {
          "nama": "Stroberi 🍓",
          "isTarget": false
        },
        {
          "nama": "Nanas 🍍",
          "isTarget": false
        }
      ],
      "id": "L_AUTO_1775323263068_3"
    },
    {
      "kategori": "urutan",
      "pertanyaan": "Urutkan angka dari yang terkecil ke terbesar!",
      "item_urutan": [
        {
          "nama": "Angka 5",
          "indexAsli": 0
        },
        {
          "nama": "Angka 6",
          "indexAsli": 1
        },
        {
          "nama": "Angka 7",
          "indexAsli": 2
        },
        {
          "nama": "Angka 8",
          "indexAsli": 3
        }
      ],
      "id": "L_AUTO_1775323263068_4"
    },
    {
      "kategori": "kuis",
      "pertanyaan": "Berapa 3 + 2?",
      "item_target": {
        "nama": "5",
        "isTarget": true
      },
      "item_pengecoh": [
        {
          "nama": "6",
          "isTarget": false
        }
      ],
      "id": "L_AUTO_1775325050357_0"
    },
    {
      "kategori": "kuis",
      "pertanyaan": "Berapa 4 + 1?",
      "item_target": {
        "nama": "5",
        "isTarget": true
      },
      "item_pengecoh": [
        {
          "nama": "6",
          "isTarget": false
        }
      ],
      "id": "L_AUTO_1775325050357_1"
    },
    {
      "id": "L_1775326220145",
      "kategori": "melayang",
      "pertanyaan": "Tekan gelembung Anggur 🍇 sebelum jatuh!",
      "speed": "cepat",
      "media_soal": null,
      "item_urutan": []
    },
    {
      "kategori": "tebak_kata",
      "pertanyaan": "Susun kata dari gambar ini: undefined",
      "item_target": {
        "nama": "APEL",
        "isTarget": true
      },
      "item_pengecoh": [
        {
          "nama": "X",
          "isTarget": false
        },
        {
          "nama": "Y",
          "isTarget": false
        }
      ],
      "id": "L_AUTO_1775325050357_3"
    },
    {
      "kategori": "tebak_kata",
      "pertanyaan": "Susun kata dari gambar ini: undefined",
      "item_target": {
        "nama": "JERUK",
        "isTarget": true
      },
      "item_pengecoh": [
        {
          "nama": "X",
          "isTarget": false
        },
        {
          "nama": "Y",
          "isTarget": false
        }
      ],
      "id": "L_AUTO_1775325050357_4"
    },
    {
      "kategori": "kuis",
      "pertanyaan": "Berapa 1 + 1?",
      "item_target": {
        "nama": "2",
        "isTarget": true
      },
      "item_pengecoh": [
        {
          "nama": "3",
          "isTarget": false
        }
      ],
      "id": "L_AUTO_1775326138818_0"
    },
    {
      "kategori": "bubble",
      "speed": "normal",
      "pertanyaan": "Tekan gelembung Pisang 🍌 sebelum jatuh!",
      "item_target": {
        "nama": "Pisang 🍌",
        "isTarget": true
      },
      "item_pengecoh": [
        {
          "nama": "Apel 🍎",
          "isTarget": false
        }
      ],
      "id": "L_AUTO_1775326138818_1"
    },
    {
      "kategori": "kuis",
      "pertanyaan": "Berapa 5 + 4?",
      "item_target": {
        "nama": "9",
        "isTarget": true
      },
      "item_pengecoh": [
        {
          "nama": "10",
          "isTarget": false
        }
      ],
      "id": "L_AUTO_1775326138818_2"
    },
    {
      "kategori": "tebak_kata",
      "pertanyaan": "Susun kata dari gambar ini: undefined",
      "item_target": {
        "nama": "APEL",
        "isTarget": true
      },
      "item_pengecoh": [
        {
          "nama": "X",
          "isTarget": false
        },
        {
          "nama": "Y",
          "isTarget": false
        }
      ],
      "id": "L_AUTO_1775326138818_3"
    },
    {
      "kategori": "kuis",
      "pertanyaan": "Berapa 1 + 1?",
      "item_target": {
        "nama": "2",
        "isTarget": true
      },
      "item_pengecoh": [
        {
          "nama": "3",
          "isTarget": false
        }
      ],
      "id": "L_AUTO_1775326138818_4"
    },
    {
      "kategori": "bubble",
      "speed": "normal",
      "pertanyaan": "Tekan gelembung Apel 🍎 sebelum jatuh!",
      "item_target": {
        "nama": "Apel 🍎",
        "isTarget": true
      },
      "item_pengecoh": [
        {
          "nama": "Pisang 🍌",
          "isTarget": false
        }
      ],
      "id": "L_AUTO_1775326142910_0"
    },
    {
      "kategori": "kuis",
      "pertanyaan": "Berapa 5 + 3?",
      "item_target": {
        "nama": "8",
        "isTarget": true
      },
      "item_pengecoh": [
        {
          "nama": "9",
          "isTarget": false
        }
      ],
      "id": "L_AUTO_1775326142910_1"
    },
    {
      "kategori": "bubble",
      "speed": "normal",
      "pertanyaan": "Tekan gelembung Apel 🍎 sebelum jatuh!",
      "item_target": {
        "nama": "Apel 🍎",
        "isTarget": true
      },
      "item_pengecoh": [
        {
          "nama": "Pisang 🍌",
          "isTarget": false
        }
      ],
      "id": "L_AUTO_1775326142910_2"
    },
    {
      "id": "L_1775326197287",
      "kategori": "melayang",
      "pertanyaan": "Tekan gelembung Anggur 🍇 sebelum jatuh!",
      "speed": "cepat",
      "media_soal": null,
      "item_urutan": []
    },
    {
      "kategori": "tebak_kata",
      "pertanyaan": "Susun kata dari gambar ini: undefined",
      "item_target": {
        "nama": "ANGGUR",
        "isTarget": true
      },
      "item_pengecoh": [
        {
          "nama": "X",
          "isTarget": false
        },
        {
          "nama": "Y",
          "isTarget": false
        }
      ],
      "id": "L_AUTO_1775326142910_4"
    }
  ]
}