{
  "global_settings": {},
  "levels": [
    {
      "id": "L_1775330807155",
      "kategori": "pukul",
      "pertanyaan": "Pukul Tikus: Tangkap 3 Jeruk 🍊!",
      "speed": "normal",
      "media_soal": "assets/msoal_1775330807155.png",
      "item_target": {
        "isTarget": true,
        "nama": "Jeruk 🍊",
        "url_gambar": "undefined"
      },
      "item_pengecoh": [
        {
          "nama": "Pisang 🍌",
          "isTarget": false
        }
      ]
    },
    {
      "kategori": "siluet",
      "pertanyaan": "Tarik Kucing 🐱 ke bayangannya!",
      "item_target": {
        "nama": "Kucing 🐱",
        "isTarget": true
      },
      "item_pengecoh": [
        {
          "nama": "Anjing 🐶",
          "isTarget": false
        }
      ],
      "id": "L_AUTO_1775330684530_1"
    },
    {
      "kategori": "kuis",
      "pertanyaan": "Berapa 1 + 2?",
      "item_target": {
        "nama": "3",
        "isTarget": true
      },
      "item_pengecoh": [
        {
          "nama": "4",
          "isTarget": false
        }
      ],
      "id": "L_AUTO_1775330684530_2"
    },
    {
      "kategori": "bubble",
      "speed": "normal",
      "pertanyaan": "Tekan gelembung Pisang 🍌!",
      "item_target": {
        "nama": "Pisang 🍌",
        "isTarget": true
      },
      "item_pengecoh": [
        {
          "nama": "Apel 🍎",
          "isTarget": false
        }
      ],
      "id": "L_AUTO_1775330684530_3"
    },
    {
      "id": "L_1775330749369",
      "kategori": "melayang",
      "pertanyaan": "Tekan gelembung Jeruk 🍊!",
      "speed": "normal",
      "media_soal": null,
      "item_urutan": [
        {
          "indexAsli": 0,
          "nama": "Satu 1"
        },
        {
          "indexAsli": 1,
          "nama": "Dua 2"
        },
        {
          "indexAsli": 2,
          "nama": "Tiga 3"
        },
        {
          "indexAsli": 3,
          "nama": "Empat 4"
        },
        {
          "indexAsli": 4,
          "nama": "5"
        },
        {
          "indexAsli": 5,
          "nama": "6"
        }
      ]
    },
    {
      "kategori": "kuis",
      "pertanyaan": "Berapa 1 + 2?",
      "item_target": {
        "nama": "3",
        "isTarget": true
      },
      "item_pengecoh": [
        {
          "nama": "4",
          "isTarget": false
        }
      ],
      "id": "L_AUTO_1775330696276_0"
    },
    {
      "kategori": "pukul",
      "speed": "normal",
      "pertanyaan": "Pukul Tikus: Tangkap 3 Pisang 🍌!",
      "item_target": {
        "nama": "Pisang 🍌",
        "isTarget": true
      },
      "item_pengecoh": [
        {
          "nama": "Apel 🍎",
          "isTarget": false
        }
      ],
      "id": "L_AUTO_1775330696276_1"
    },
    {
      "kategori": "tebak_kata",
      "pertanyaan": "Susun kata: undefined",
      "item_target": {
        "nama": "APEL",
        "isTarget": true
      },
      "item_pengecoh": [
        {
          "nama": "X",
          "isTarget": false
        }
      ],
      "id": "L_AUTO_1775330696276_2"
    },
    {
      "kategori": "siluet",
      "pertanyaan": "Tarik Ikan 🐟 ke bayangannya!",
      "item_target": {
        "nama": "Ikan 🐟",
        "isTarget": true
      },
      "item_pengecoh": [
        {
          "nama": "Anjing 🐶",
          "isTarget": false
        }
      ],
      "id": "L_AUTO_1775330696276_3"
    },
    {
      "kategori": "pukul",
      "speed": "normal",
      "pertanyaan": "Pukul Tikus: Tangkap 3 Jeruk 🍊!",
      "item_target": {
        "nama": "Jeruk 🍊",
        "isTarget": true
      },
      "item_pengecoh": [
        {
          "nama": "Pisang 🍌",
          "isTarget": false
        }
      ],
      "id": "L_AUTO_1775330696276_4"
    }
  ]
}